agi_corex-0.1.0.dist-info/licenses/LICENSE.md
agi_lab/agents/_init_.py
agi_lab/agents/base.py
agi_lab/agents/genetic.py
agi_lab/agents/neuromorphic.py
agi_lab/enviroments/_init_.py
agi_lab/enviroments/env_base.py
agi_lab/evaluation/_init_.py
agi_lab/evaluation/metrics.py
agi_lab/learning/_init_.py
agi_lab/learning/evolutionary.py
agi_lab/learning/meta_learning.py
agi_lab/learning/plasticity.py
agi_lab/memory/_init_.py
agi_lab/memory/sub_symbolic.py
agi_lab/memory/symbolic.py
agi_lab/reasoning/_init_.py
agi_lab/reasoning/neuro_symbolic.py
agi_corex-0.1.0.dist-info/METADATA
agi_corex-0.1.0.dist-info/WHEEL
agi_corex-0.1.0.dist-info/top_level.txt
agi_corex-0.1.0.dist-info/RECORD
