Metadata-Version: 2.4
Name: agi-corex
Version: 0.1.0
Summary: Experimental AGI framework with neuro-symbolic reasoning, evolutionary agents and plastic learning
Author-email: Adolfo <tu-email@example.com>
License-Expression: MIT
Requires-Python: >=3.8
License-File: LICENSE.md
Requires-Dist: numpy
Requires-Dist: scipy
Requires-Dist: matplotlib
Requires-Dist: networkx
Dynamic: license-file
